snowflake/__init__.py
snowflake/ingest/__init__.py
snowflake/ingest/streaming/__init__.py
snowflake/ingest/streaming/_python_ffi.abi3.so
snowflake/ingest/streaming/_utils.py
snowflake/ingest/streaming/_version.py
snowflake/ingest/streaming/channel_status.py
snowflake/ingest/streaming/streaming_ingest_channel.py
snowflake/ingest/streaming/streaming_ingest_client.py
snowflake/ingest/streaming/streaming_ingest_error.py
snowpipe_streaming-1.1.2.dist-info/METADATA
snowpipe_streaming-1.1.2.dist-info/WHEEL
snowpipe_streaming-1.1.2.dist-info/licenses/LICENSE-2.0.txt
snowpipe_streaming-1.1.2.dist-info/RECORD
