Metadata-Version: 2.4
Name: snowpipe-streaming
Version: 1.1.2
Classifier: Intended Audience :: Developers
Classifier: License :: OSI Approved :: Apache Software License
Classifier: Programming Language :: Python :: 3
Classifier: Programming Language :: Python :: 3.9
Classifier: Programming Language :: Python :: 3.10
Classifier: Programming Language :: Python :: 3.11
Classifier: Programming Language :: Python :: 3.12
Classifier: Programming Language :: Python :: 3.13
Classifier: Programming Language :: Rust
Classifier: Topic :: Database
Requires-Dist: msgspec==0.19.0
Requires-Dist: pytest>=8.3.5 ; extra == 'dev'
Requires-Dist: maturin==1.9.0 ; extra == 'dev'
Provides-Extra: dev
License-File: LICENSE-2.0.txt
Summary: Snowflake Streaming Ingest SDK
Keywords: snowflake,streaming,ingest,data
Author-email: "Snowflake Inc." <support@snowflake.com>
License: MIT or Apache-2.0
Requires-Python: >=3.9
Project-URL: Homepage, https://github.com/snowflakedb/snowflake-ingest-sdk
Project-URL: Repository, https://github.com/snowflakedb/snowflake-ingest-sdk
Project-URL: Documentation, https://docs.snowflake.com/
